vxapi/__init__.py
vxapi/exceptions.py
vxapi/vxapi.py
vxapi-1.1.dist-info/METADATA
vxapi-1.1.dist-info/WHEEL
vxapi-1.1.dist-info/top_level.txt
vxapi-1.1.dist-info/RECORD
