Metadata-Version: 2.1
Name: vxapi
Version: 1.1
Summary: virus.exchange wrapper for python
Home-page: https://github.com/clienthold/vxapi
Author: Dmitry Kondrashov
Requires-Python: >=3.7, <4
Requires-Dist: requests
